{"name":"698.edges","nodes":61,"dir_edges":0,"und_edges":270,"data":{"697":{"edges":[{"to":"828","directed":false},{"to":"890","directed":false},{"to":"830","directed":false},{"to":"753","directed":false},{"to":"800","directed":false},{"to":"823","directed":false},{"to":"719","directed":false},{"to":"747","directed":false},{"to":"819","directed":false},{"to":"840","directed":false},{"to":"772","directed":false},{"to":"745","directed":false},{"to":"856","directed":false},{"to":"708","directed":false},{"to":"713","directed":false},{"to":"769","directed":false},{"to":"805","directed":false}],"features":{"personalData":{"first_name":"Hassie","middle_name":"Emmie","last_name":"Mills","gender":"female","avatar_url":"https://randomuser.me/api/portraits/women/13.jpg"},"workData":{"employer_id":"Zboncak - Kiehn","from_id":null,"with_id":null,"location":"14328 East Brittanyland","position":"Regional Optimization Representative","projects":["Gorgeous Steel Keyboard","Refined Metal Car","Fantastic Frozen Gloves"]},"locationData":{"hometown":"51120 Frankchester","location":"08687 West Alvisfurt","languages":["English","Oromo"],"locale":"en_US"},"profileDates":{"work_end_date":"2016-07-21T14:25:21.513Z","work_start_date":"1996-10-10T21:36:29.379Z","graduation_date":"1995-06-21T04:37:13.534Z","birth_date":"1975-06-26T04:37:13.000Z"},"coords":{"x":229,"y":262,"z":382}},"coords":{"x":229,"y":262,"z":382}},"703":{"edges":[{"to":"828","directed":false},{"to":"819","directed":false},{"to":"747","directed":false},{"to":"805","directed":false},{"to":"823","directed":false},{"to":"880","directed":false},{"to":"856","directed":false},{"to":"719","directed":false}],"features":{"personalData":{"first_name":"Mitchel","middle_name":"Spencer","last_name":"Kuhn","gender":"male","avatar_url":"https://randomuser.me/api/portraits/men/53.jpg"},"workData":{"employer_id":"D'Amore, Mayert and Larkin","from_id":null,"with_id":null,"location":"32941 Braedenmouth","position":"District Implementation Developer","projects":["Ergonomic Frozen Gloves","Incredible Metal Computer","Intelligent Granite Pizza"]},"locationData":{"hometown":"22273 Bettyfort","location":"44956 Zariahaven","languages":["English","Hmong"],"locale":"en_US"},"profileDates":{"work_end_date":"2015-11-18T21:25:16.664Z","work_start_date":"2003-09-04T22:21:59.708Z","graduation_date":"2002-10-26T16:41:57.353Z","birth_date":"1982-10-31T16:41:57.000Z"},"coords":{"x":328,"y":225,"z":412}},"coords":{"x":328,"y":225,"z":412}},"708":{"edges":[{"to":"823","directed":false},{"to":"869","directed":false},{"to":"819","directed":false},{"to":"856","directed":false},{"to":"830","directed":false},{"to":"753","directed":false},{"to":"890","directed":false},{"to":"840","directed":false},{"to":"713","directed":false},{"to":"747","directed":false},{"to":"774","directed":false},{"to":"769","directed":false},{"to":"811","directed":false},{"to":"719","directed":false},{"to":"697","directed":false},{"to":"828","directed":false},{"to":"800","directed":false}],"features":{"personalData":{"first_name":"Augustus","middle_name":"Kenton","last_name":"Yundt","gender":"male","avatar_url":"https://randomuser.me/api/portraits/men/45.jpg"},"workData":{"employer_id":"Pacocha - Bernhard","from_id":null,"with_id":null,"location":"14254 Heaneyton","position":"Internal Factors Manager","projects":["Handcrafted Cotton Shirt"]},"locationData":{"hometown":"59471 North Nealfort","location":"25715 East Pete","languages":["English","Kannada","Russian"],"locale":"en_US"},"profileDates":{"work_end_date":"2015-11-15T19:20:44.720Z","work_start_date":"2002-02-25T06:57:11.483Z","graduation_date":"2000-12-15T04:26:08.193Z","birth_date":"1980-12-20T04:26:08.000Z"},"coords":{"x":27,"y":56,"z":303}},"coords":{"x":27,"y":56,"z":303}},"713":{"edges":[{"to":"719","directed":false},{"to":"819","directed":false},{"to":"772","directed":false},{"to":"805","directed":false},{"to":"823","directed":false},{"to":"830","directed":false},{"to":"747","directed":false},{"to":"708","directed":false},{"to":"774","directed":false},{"to":"800","directed":false},{"to":"810","directed":false},{"to":"840","directed":false},{"to":"697","directed":false},{"to":"745","directed":false},{"to":"828","directed":false}],"features":{"personalData":{"first_name":"Keven","middle_name":"Wyatt","last_name":"Kirlin","gender":"male","avatar_url":"https://randomuser.me/api/portraits/men/94.jpg"},"workData":{"employer_id":"Ondricka, Simonis and Anderson","from_id":null,"with_id":null,"location":"16588 Holliebury","position":"Senior Implementation Manager","projects":["Incredible Metal Table","Generic Metal Gloves","Handcrafted Steel Table"]},"locationData":{"hometown":"47965 Adamsfurt","location":"93972 South Myrtieside","languages":["English","Tamil","Northern","Mandarin","Russian"],"locale":"en_US"},"profileDates":{"work_end_date":"2016-03-07T10:16:50.925Z","work_start_date":"2001-04-28T12:28:43.672Z","graduation_date":"2000-01-22T20:16:49.650Z","birth_date":"1980-01-27T20:16:49.000Z"},"coords":{"x":75,"y":58,"z":90}},"coords":{"x":75,"y":58,"z":90}},"719":{"edges":[{"to":"713","directed":false},{"to":"840","directed":false},{"to":"819","directed":false},{"to":"810","directed":false},{"to":"747","directed":false},{"to":"772","directed":false},{"to":"774","directed":false},{"to":"800","directed":false},{"to":"823","directed":false},{"to":"697","directed":false},{"to":"708","directed":false},{"to":"830","directed":false},{"to":"805","directed":false},{"to":"745","directed":false},{"to":"828","directed":false},{"to":"703","directed":false}],"features":{"personalData":{"first_name":"Chet","middle_name":"Duane","last_name":"Brekke","gender":"male","avatar_url":"https://randomuser.me/api/portraits/men/47.jpg"},"workData":{"employer_id":"Kling - Feil","from_id":null,"with_id":null,"location":"99780 Mckaylaville","position":"Regional Creative Designer","projects":["Rustic Concrete Car","Handcrafted Concrete Cheese","Refined Rubber Mouse"]},"locationData":{"hometown":"27445 Port Evalyn","location":"24729 Kevonborough","languages":["English","Dhundhari","Arabic"],"locale":"en_US"},"profileDates":{"work_end_date":"2017-04-06T13:36:24.090Z","work_start_date":"2008-10-25T05:39:48.644Z","graduation_date":"2008-01-12T17:45:21.378Z","birth_date":"1988-01-17T17:45:21.000Z"},"coords":{"x":340,"y":225,"z":17}},"coords":{"x":340,"y":225,"z":17}},"729":{"edges":[{"to":"888","directed":false},{"to":"861","directed":false},{"to":"876","directed":false},{"to":"882","directed":false},{"to":"804","directed":false},{"to":"889","directed":false},{"to":"886","directed":false},{"to":"753","directed":false},{"to":"856","directed":false},{"to":"863","directed":false},{"to":"878","directed":false}],"features":{"personalData":{"first_name":"Shana","middle_name":"Ebony","last_name":"Fritsch","gender":"female","avatar_url":"https://randomuser.me/api/portraits/women/6.jpg"},"workData":{"employer_id":"Conn LLC","from_id":null,"with_id":null,"location":"24054 North Keaton","position":"Central Brand Liason","projects":["Practical Soft Computer"]},"locationData":{"hometown":"45406 Port Kasandrafurt","location":"69963 Jaymeton","languages":["English","Tamil","Malayalam"],"locale":"en_US"},"profileDates":{"work_end_date":"2016-08-04T01:46:54.038Z","work_start_date":"2011-05-01T15:32:15.573Z","graduation_date":"2010-02-05T00:22:54.804Z","birth_date":"1990-02-10T00:22:54.000Z"},"coords":{"x":478,"y":257,"z":448}},"coords":{"x":478,"y":257,"z":448}},"745":{"edges":[{"to":"805","directed":false},{"to":"830","directed":false},{"to":"810","directed":false},{"to":"747","directed":false},{"to":"800","directed":false},{"to":"697","directed":false},{"to":"774","directed":false},{"to":"828","directed":false},{"to":"719","directed":false},{"to":"823","directed":false},{"to":"713","directed":false}],"features":{"personalData":{"first_name":"Monica","middle_name":"Bridgette","last_name":"Feil","gender":"female","avatar_url":"https://randomuser.me/api/portraits/women/40.jpg"},"workData":{"employer_id":"Cummings, Homenick and Murray","from_id":null,"with_id":null,"location":"79848 New Irma","position":"Corporate Research Producer","projects":["Tasty Fresh Mouse","Sleek Cotton Pants","Practical Plastic Soap"]},"locationData":{"hometown":"50351 South Eriktown","location":"72291 Connhaven","languages":["English","Mandarin","Hindi","Saraiki"],"locale":"en_US"},"profileDates":{"work_end_date":"2016-06-28T19:19:07.142Z","work_start_date":"2015-03-16T04:14:33.926Z","graduation_date":"2013-12-06T19:11:40.250Z","birth_date":"1993-12-11T19:11:40.000Z"},"coords":{"x":130,"y":288,"z":108}},"coords":{"x":130,"y":288,"z":108}},"747":{"edges":[{"to":"830","directed":false},{"to":"856","directed":false},{"to":"819","directed":false},{"to":"719","directed":false},{"to":"810","directed":false},{"to":"745","directed":false},{"to":"713","directed":false},{"to":"708","directed":false},{"to":"774","directed":false},{"to":"804","directed":false},{"to":"769","directed":false},{"to":"703","directed":false},{"to":"803","directed":false},{"to":"697","directed":false},{"to":"800","directed":false},{"to":"823","directed":false},{"to":"805","directed":false},{"to":"880","directed":false},{"to":"828","directed":false},{"to":"840","directed":false},{"to":"753","directed":false}],"features":{"personalData":{"first_name":"Everette","middle_name":"Ahmed","last_name":"Ebert","gender":"male","avatar_url":"https://randomuser.me/api/portraits/men/72.jpg"},"workData":{"employer_id":"Dare - Brakus","from_id":null,"with_id":null,"location":"26175 South Arnold","position":"Corporate Markets Specialist","projects":["Handmade Fresh Fish","Gorgeous Granite Sausages","Rustic Soft Soap"]},"locationData":{"hometown":"16149 Jaylinhaven","location":"66135 Considineton","languages":["English","Ilocano","Shona","Spanish"],"locale":"en_US"},"profileDates":{"work_end_date":"2016-08-16T19:18:23.449Z","work_start_date":"2011-09-07T12:59:54.457Z","graduation_date":"2010-12-25T13:42:11.174Z","birth_date":"1990-12-30T13:42:11.000Z"},"coords":{"x":507,"y":246,"z":228}},"coords":{"x":507,"y":246,"z":228}},"753":{"edges":[{"to":"823","directed":false},{"to":"890","directed":false},{"to":"889","directed":false},{"to":"708","directed":false},{"to":"697","directed":false},{"to":"769","directed":false},{"to":"819","directed":false},{"to":"729","directed":false},{"to":"856","directed":false},{"to":"861","directed":false},{"to":"747","directed":false}],"features":{"personalData":{"first_name":"Alex","middle_name":"Angelo","last_name":"Mann","gender":"male","avatar_url":"https://randomuser.me/api/portraits/men/67.jpg"},"workData":{"employer_id":"Bechtelar, Goyette and Lebsack","from_id":null,"with_id":null,"location":"03258 Lake Edwardton","position":"Senior Optimization Administrator","projects":["Awesome Rubber Computer","Fantastic Wooden Keyboard","Ergonomic Metal Salad"]},"locationData":{"hometown":"77421 Port Alexaburgh","location":"17443 Lake Alexys","languages":["English","Bengali","Javanese"],"locale":"en_US"},"profileDates":{"work_end_date":"2016-03-29T13:21:09.248Z","work_start_date":"2010-01-24T13:36:12.423Z","graduation_date":"2008-07-15T20:57:27.960Z","birth_date":"1988-07-20T20:57:27.000Z"},"coords":{"x":158,"y":74,"z":494}},"coords":{"x":158,"y":74,"z":494}},"769":{"edges":[{"to":"869","directed":false},{"to":"774","directed":false},{"to":"811","directed":false},{"to":"753","directed":false},{"to":"828","directed":false},{"to":"747","directed":false},{"to":"708","directed":false},{"to":"800","directed":false},{"to":"890","directed":false},{"to":"856","directed":false},{"to":"798","directed":false},{"to":"697","directed":false}],"features":{"personalData":{"first_name":"Ambrose","middle_name":"Ken","last_name":"Tromp","gender":"male","avatar_url":"https://randomuser.me/api/portraits/men/48.jpg"},"workData":{"employer_id":"Wilderman Inc","from_id":null,"with_id":null,"location":"48311 Ernaville","position":"District Usability Developer","projects":["Practical Metal Keyboard","Small Cotton Fish"]},"locationData":{"hometown":"57174 Port Rexmouth","location":"24393 Stromanborough","languages":["English","Korean","Khmer","Marwari","Russian"],"locale":"en_US"},"profileDates":{"work_end_date":"2016-02-02T18:48:04.426Z","work_start_date":"2004-07-13T04:59:28.903Z","graduation_date":"2004-04-17T00:27:29.562Z","birth_date":"1984-04-22T00:27:29.000Z"},"coords":{"x":315,"y":288,"z":207}},"coords":{"x":315,"y":288,"z":207}},"772":{"edges":[{"to":"828","directed":false},{"to":"719","directed":false},{"to":"713","directed":false},{"to":"805","directed":false},{"to":"856","directed":false},{"to":"800","directed":false},{"to":"697","directed":false}],"features":{"personalData":{"first_name":"Layne","middle_name":"Stephany","last_name":"Kirlin","gender":"female","avatar_url":"https://randomuser.me/api/portraits/women/55.jpg"},"workData":{"employer_id":"O'Kon Group","from_id":null,"with_id":null,"location":"13949 South Broderick","position":"Internal Integration Coordinator","projects":["Small Granite Shoes","Handcrafted Frozen Shirt","Tasty Plastic Car"]},"locationData":{"hometown":"84117 Feltonview","location":"38636 Harberchester","languages":["English","Mandarin","Punjabi","French","Turkish"],"locale":"en_US"},"profileDates":{"work_end_date":"2017-02-18T16:32:50.687Z","work_start_date":"2003-05-04T05:22:39.658Z","graduation_date":"2002-06-23T02:06:52.963Z","birth_date":"1982-06-28T02:06:52.000Z"},"coords":{"x":496,"y":388,"z":70}},"coords":{"x":496,"y":388,"z":70}},"774":{"edges":[{"to":"869","directed":false},{"to":"769","directed":false},{"to":"856","directed":false},{"to":"810","directed":false},{"to":"805","directed":false},{"to":"719","directed":false},{"to":"800","directed":false},{"to":"713","directed":false},{"to":"811","directed":false},{"to":"747","directed":false},{"to":"708","directed":false},{"to":"745","directed":false},{"to":"823","directed":false},{"to":"819","directed":false},{"to":"828","directed":false},{"to":"840","directed":false},{"to":"830","directed":false}],"features":{"personalData":{"first_name":"Velva","middle_name":"Treva","last_name":"Emmerich","gender":"female","avatar_url":"https://randomuser.me/api/portraits/women/59.jpg"},"workData":{"employer_id":"Friesen LLC","from_id":null,"with_id":null,"location":"87863 New Reynoldmouth","position":"Dynamic Integration Coordinator","projects":["Fantastic Plastic Ball","Intelligent Frozen Pants"]},"locationData":{"hometown":"93986 Asaside","location":"13466 Mylesburgh","languages":["English","Mandarin","Japanese","Odia","Bengali"],"locale":"en_US"},"profileDates":{"work_end_date":"2017-03-16T04:38:49.656Z","work_start_date":"2001-03-26T03:03:38.803Z","graduation_date":"2000-08-19T20:38:36.305Z","birth_date":"1980-08-24T20:38:36.000Z"},"coords":{"x":313,"y":332,"z":428}},"coords":{"x":313,"y":332,"z":428}},"776":{"edges":[{"to":"874","directed":false},{"to":"887","directed":false},{"to":"867","directed":false},{"to":"873","directed":false},{"to":"885","directed":false},{"to":"872","directed":false},{"to":"877","directed":false}],"features":{"personalData":{"first_name":"Constance","middle_name":"Molly","last_name":"Littel","gender":"female","avatar_url":"https://randomuser.me/api/portraits/women/99.jpg"},"workData":{"employer_id":"Schoen - Luettgen","from_id":null,"with_id":null,"location":"70755 New Gabriella","position":"Internal Metrics Officer","projects":["Rustic Rubber Mouse","Licensed Soft Fish","Awesome Steel Soap"]},"locationData":{"hometown":"66340 Adanfort","location":"76413 New Emelieland","languages":["English","Kazakh","Urdu"],"locale":"en_US"},"profileDates":{"work_end_date":"2016-07-21T23:48:25.850Z","work_start_date":"1999-11-25T08:05:59.766Z","graduation_date":"1999-03-30T04:03:20.102Z","birth_date":"1979-04-04T04:03:20.000Z"},"coords":{"x":422,"y":238,"z":128}},"coords":{"x":422,"y":238,"z":128}},"798":{"edges":[{"to":"769","directed":false}],"features":{"personalData":{"first_name":"Jillian","middle_name":"Damaris","last_name":"Walsh","gender":"female","avatar_url":"https://randomuser.me/api/portraits/women/97.jpg"},"workData":{"employer_id":"Labadie, Halvorson and Leannon","from_id":null,"with_id":null,"location":"80845 Emmanuelleborough","position":"Global Usability Planner","projects":["Ergonomic Metal Shoes"]},"locationData":{"hometown":"45891 East Kaelynborough","location":"27490 Port Tyreeborough","languages":["English","Gujarati","Malayalam","Malay","Mandarin"],"locale":"en_US"},"profileDates":{"work_end_date":"2016-08-06T09:55:14.066Z","work_start_date":"2015-12-07T12:46:20.101Z","graduation_date":"2015-06-17T07:54:35.353Z","birth_date":"1995-06-22T07:54:35.000Z"},"coords":{"x":197,"y":83,"z":54}},"coords":{"x":197,"y":83,"z":54}},"800":{"edges":[{"to":"805","directed":false},{"to":"810","directed":false},{"to":"830","directed":false},{"to":"719","directed":false},{"to":"774","directed":false},{"to":"772","directed":false},{"to":"697","directed":false},{"to":"811","directed":false},{"to":"745","directed":false},{"to":"713","directed":false},{"to":"769","directed":false},{"to":"747","directed":false},{"to":"823","directed":false},{"to":"856","directed":false},{"to":"828","directed":false},{"to":"708","directed":false}],"features":{"personalData":{"first_name":"Carmine","middle_name":"Rick","last_name":"O'Connell","gender":"male","avatar_url":"https://randomuser.me/api/portraits/men/86.jpg"},"workData":{"employer_id":"Hickle, Schroeder and Oberbrunner","from_id":null,"with_id":null,"location":"29683 Port Davinborough","position":"Central Communications Consultant","projects":["Handmade Soft Salad","Intelligent Rubber Salad","Intelligent Steel Gloves"]},"locationData":{"hometown":"22221 New Dedric","location":"48563 Reichelborough","languages":["English","Marathi","Mandarin"],"locale":"en_US"},"profileDates":{"work_end_date":"2015-10-18T01:24:55.001Z","work_start_date":"2009-08-18T04:08:15.279Z","graduation_date":"2009-08-13T20:49:36.659Z","birth_date":"1989-08-18T20:49:36.000Z"},"coords":{"x":63,"y":410,"z":62}},"coords":{"x":63,"y":410,"z":62}},"803":{"edges":[{"to":"840","directed":false},{"to":"747","directed":false},{"to":"880","directed":false}],"features":{"personalData":{"first_name":"Cleta","middle_name":"Shana","last_name":"Rowe","gender":"female","avatar_url":"https://randomuser.me/api/portraits/women/6.jpg"},"workData":{"employer_id":"Feil Group","from_id":null,"with_id":null,"location":"53042 Prohaskaland","position":"International Marketing Liason","projects":["Rustic Rubber Bike","Generic Granite Pizza","Unbranded Steel Sausages"]},"locationData":{"hometown":"64592 Lake Omerfort","location":"06441 East Jonatanmouth","languages":["English","Mandarin","Vietnamese","Korean"],"locale":"en_US"},"profileDates":{"work_end_date":"2016-11-17T12:20:21.873Z","work_start_date":"2013-09-15T05:52:28.827Z","graduation_date":"2013-03-23T09:39:31.150Z","birth_date":"1993-03-28T09:39:31.000Z"},"coords":{"x":190,"y":20,"z":57}},"coords":{"x":190,"y":20,"z":57}},"804":{"edges":[{"to":"888","directed":false},{"to":"861","directed":false},{"to":"729","directed":false},{"to":"863","directed":false},{"to":"856","directed":false},{"to":"876","directed":false},{"to":"747","directed":false},{"to":"886","directed":false},{"to":"882","directed":false},{"to":"878","directed":false},{"to":"889","directed":false}],"features":{"personalData":{"first_name":"Cyrus","middle_name":"Bernie","last_name":"Daugherty","gender":"male","avatar_url":"https://randomuser.me/api/portraits/men/68.jpg"},"workData":{"employer_id":"Gutmann, Barton and Schumm","from_id":null,"with_id":null,"location":"27646 North Ramon","position":"National Division Manager","projects":["Incredible Granite Chair","Refined Fresh Tuna"]},"locationData":{"hometown":"87929 New Charityton","location":"54892 Kurtisburgh","languages":["English","Dutch","Thai"],"locale":"en_US"},"profileDates":{"work_end_date":"2016-01-27T07:14:13.521Z","work_start_date":"2015-04-07T12:57:52.473Z","graduation_date":"2015-01-19T19:15:06.721Z","birth_date":"1995-01-24T19:15:06.000Z"},"coords":{"x":444,"y":343,"z":509}},"coords":{"x":444,"y":343,"z":509}},"805":{"edges":[{"to":"745","directed":false},{"to":"800","directed":false},{"to":"774","directed":false},{"to":"772","directed":false},{"to":"713","directed":false},{"to":"830","directed":false},{"to":"823","directed":false},{"to":"703","directed":false},{"to":"880","directed":false},{"to":"747","directed":false},{"to":"719","directed":false},{"to":"819","directed":false},{"to":"697","directed":false},{"to":"810","directed":false},{"to":"828","directed":false},{"to":"840","directed":false}],"features":{"personalData":{"first_name":"Darrin","middle_name":"Rolando","last_name":"Mann","gender":"male","avatar_url":"https://randomuser.me/api/portraits/men/10.jpg"},"workData":{"employer_id":"Lemke Group","from_id":null,"with_id":null,"location":"57819 West Hassiechester","position":"Central Response Director","projects":["Gorgeous Steel Computer"]},"locationData":{"hometown":"83841 Lake Ebba","location":"26050 Lake Guidoview","languages":["English","Russian","Persian","Mandarin","Awadhi"],"locale":"en_US"},"profileDates":{"work_end_date":"2015-12-20T15:37:42.905Z","work_start_date":"2013-12-28T13:39:13.111Z","graduation_date":"2013-10-08T22:38:21.478Z","birth_date":"1993-10-13T22:38:21.000Z"},"coords":{"x":206,"y":467,"z":350}},"coords":{"x":206,"y":467,"z":350}},"810":{"edges":[{"to":"823","directed":false},{"to":"719","directed":false},{"to":"774","directed":false},{"to":"828","directed":false},{"to":"800","directed":false},{"to":"747","directed":false},{"to":"745","directed":false},{"to":"856","directed":false},{"to":"713","directed":false},{"to":"805","directed":false}],"features":{"personalData":{"first_name":"Antoinette","middle_name":"Zora","last_name":"O'Reilly","gender":"female","avatar_url":"https://randomuser.me/api/portraits/women/30.jpg"},"workData":{"employer_id":"Paucek, Boyle and Schimmel","from_id":null,"with_id":null,"location":"46560 Rodriguezton","position":"Corporate Accountability Developer","projects":["Fantastic Soft Chips","Generic Rubber Cheese","Fantastic Fresh Hat"]},"locationData":{"hometown":"83204 Schuppeville","location":"85094 South Donnaville","languages":["English","Spanish","Kirundi"],"locale":"en_US"},"profileDates":{"work_end_date":"2015-09-10T11:02:43.749Z","work_start_date":"2002-10-09T10:50:15.764Z","graduation_date":"2002-01-08T03:20:52.656Z","birth_date":"1982-01-13T03:20:52.000Z"},"coords":{"x":242,"y":397,"z":117}},"coords":{"x":242,"y":397,"z":117}},"811":{"edges":[{"to":"769","directed":false},{"to":"856","directed":false},{"to":"800","directed":false},{"to":"774","directed":false},{"to":"869","directed":false},{"to":"890","directed":false},{"to":"708","directed":false}],"features":{"personalData":{"first_name":"Hiram","middle_name":"Jonathon","last_name":"Bechtelar","gender":"male","avatar_url":"https://randomuser.me/api/portraits/men/94.jpg"},"workData":{"employer_id":"Hermann - Shields","from_id":null,"with_id":null,"location":"40265 New Mattieborough","position":"International Markets Coordinator","projects":["Awesome Concrete Tuna"]},"locationData":{"hometown":"81380 Ernserton","location":"60312 East Summerburgh","languages":["English","German","Sundanese","Portuguese"],"locale":"en_US"},"profileDates":{"work_end_date":"2016-06-03T22:38:19.488Z","work_start_date":"2001-06-23T11:35:49.100Z","graduation_date":"2001-03-17T22:30:49.260Z","birth_date":"1981-03-22T22:30:49.000Z"},"coords":{"x":431,"y":4,"z":345}},"coords":{"x":431,"y":4,"z":345}},"819":{"edges":[{"to":"713","directed":false},{"to":"719","directed":false},{"to":"747","directed":false},{"to":"708","directed":false},{"to":"823","directed":false},{"to":"828","directed":false},{"to":"880","directed":false},{"to":"753","directed":false},{"to":"703","directed":false},{"to":"697","directed":false},{"to":"774","directed":false},{"to":"805","directed":false},{"to":"840","directed":false},{"to":"830","directed":false},{"to":"856","directed":false}],"features":{"personalData":{"first_name":"Mauricio","middle_name":"Myles","last_name":"Jakubowski","gender":"male","avatar_url":"https://randomuser.me/api/portraits/men/94.jpg"},"workData":{"employer_id":"Bashirian, McCullough and Lang","from_id":null,"with_id":null,"location":"17869 New Geraldmouth","position":"Customer Intranet Engineer","projects":["Generic Cotton Pants","Licensed Frozen Pants"]},"locationData":{"hometown":"15173 North Josefinaborough","location":"27477 Flatleytown","languages":["English","Bengali","Portuguese"],"locale":"en_US"},"profileDates":{"work_end_date":"2016-04-11T19:25:13.840Z","work_start_date":"2006-04-30T22:07:50.371Z","graduation_date":"2004-11-06T21:47:05.962Z","birth_date":"1984-11-11T21:47:05.000Z"},"coords":{"x":267,"y":346,"z":333}},"coords":{"x":267,"y":346,"z":333}},"823":{"edges":[{"to":"708","directed":false},{"to":"840","directed":false},{"to":"810","directed":false},{"to":"753","directed":false},{"to":"819","directed":false},{"to":"713","directed":false},{"to":"719","directed":false},{"to":"805","directed":false},{"to":"697","directed":false},{"to":"830","directed":false},{"to":"703","directed":false},{"to":"856","directed":false},{"to":"747","directed":false},{"to":"800","directed":false},{"to":"828","directed":false},{"to":"880","directed":false},{"to":"774","directed":false},{"to":"745","directed":false}],"features":{"personalData":{"first_name":"Carley","middle_name":"Lola","last_name":"Mann","gender":"female","avatar_url":"https://randomuser.me/api/portraits/women/9.jpg"},"workData":{"employer_id":"Veum, Beier and Murazik","from_id":null,"with_id":null,"location":"02605 Sierrafort","position":"Customer Implementation Orchestrator","projects":["Gorgeous Cotton Computer","Sleek Wooden Gloves"]},"locationData":{"hometown":"93355 East Kaleighshire","location":"10807 Goodwinburgh","languages":["English","French","Urdu","Hindi","Arabic"],"locale":"en_US"},"profileDates":{"work_end_date":"2017-01-09T17:27:23.300Z","work_start_date":"1999-11-01T11:40:08.705Z","graduation_date":"1999-03-27T22:17:27.058Z","birth_date":"1979-04-01T22:17:27.000Z"},"coords":{"x":91,"y":5,"z":506}},"coords":{"x":91,"y":5,"z":506}},"825":{"edges":[{"to":"889","directed":false},{"to":"884","directed":false},{"to":"856","directed":false},{"to":"864","directed":false}],"features":{"personalData":{"first_name":"Vaughn","middle_name":"Nicholas","last_name":"Witting","gender":"male","avatar_url":"https://randomuser.me/api/portraits/men/23.jpg"},"workData":{"employer_id":"Sporer, Murphy and Purdy","from_id":null,"with_id":null,"location":"61964 Braunberg","position":"Legacy Integration Technician","projects":["Tasty Steel Chicken","Unbranded Steel Table","Sleek Concrete Soap"]},"locationData":{"hometown":"41225 Port Tyrellville","location":"53423 Kuhnmouth","languages":["English","Arabic","Korean","Russian"],"locale":"en_US"},"profileDates":{"work_end_date":"2016-11-15T09:39:36.772Z","work_start_date":"2005-05-18T16:45:14.073Z","graduation_date":"2005-03-20T13:39:01.504Z","birth_date":"1985-03-25T13:39:01.000Z"},"coords":{"x":87,"y":268,"z":0}},"coords":{"x":87,"y":268,"z":0}},"828":{"edges":[{"to":"697","directed":false},{"to":"772","directed":false},{"to":"810","directed":false},{"to":"819","directed":false},{"to":"856","directed":false},{"to":"880","directed":false},{"to":"703","directed":false},{"to":"769","directed":false},{"to":"830","directed":false},{"to":"823","directed":false},{"to":"745","directed":false},{"to":"800","directed":false},{"to":"840","directed":false},{"to":"708","directed":false},{"to":"774","directed":false},{"to":"747","directed":false},{"to":"713","directed":false},{"to":"719","directed":false},{"to":"805","directed":false}],"features":{"personalData":{"first_name":"Tia","middle_name":"Wilma","last_name":"Moore","gender":"female","avatar_url":"https://randomuser.me/api/portraits/women/40.jpg"},"workData":{"employer_id":"Raynor - Dickinson","from_id":null,"with_id":null,"location":"22014 Mrazbury","position":"Senior Division Coordinator","projects":["Intelligent Frozen Chicken","Awesome Plastic Soap","Licensed Wooden Tuna"]},"locationData":{"hometown":"03088 Britneyview","location":"91060 South Mellie","languages":["English","Malay","Portuguese","Spanish"],"locale":"en_US"},"profileDates":{"work_end_date":"2015-12-26T06:53:25.376Z","work_start_date":"1996-05-29T20:03:06.507Z","graduation_date":"1995-08-01T06:13:09.415Z","birth_date":"1975-08-06T06:13:09.000Z"},"coords":{"x":363,"y":457,"z":111}},"coords":{"x":363,"y":457,"z":111}},"830":{"edges":[{"to":"745","directed":false},{"to":"747","directed":false},{"to":"708","directed":false},{"to":"697","directed":false},{"to":"800","directed":false},{"to":"713","directed":false},{"to":"805","directed":false},{"to":"823","directed":false},{"to":"840","directed":false},{"to":"828","directed":false},{"to":"719","directed":false},{"to":"856","directed":false},{"to":"819","directed":false},{"to":"774","directed":false}],"features":{"personalData":{"first_name":"Ervin","middle_name":"Andres","last_name":"Ritchie","gender":"male","avatar_url":"https://randomuser.me/api/portraits/men/99.jpg"},"workData":{"employer_id":"Strosin LLC","from_id":null,"with_id":null,"location":"96661 East Shayne","position":"Direct Markets Developer","projects":["Unbranded Soft Bacon","Generic Granite Car","Small Fresh Keyboard"]},"locationData":{"hometown":"18518 Jimmieborough","location":"37070 South Aida","languages":["English","Maithili","Yue","Xiang"],"locale":"en_US"},"profileDates":{"work_end_date":"2016-01-05T03:43:05.344Z","work_start_date":"1997-05-21T05:25:28.782Z","graduation_date":"1995-08-13T01:12:52.659Z","birth_date":"1975-08-18T01:12:52.000Z"},"coords":{"x":280,"y":397,"z":443}},"coords":{"x":280,"y":397,"z":443}},"840":{"edges":[{"to":"803","directed":false},{"to":"719","directed":false},{"to":"823","directed":false},{"to":"708","directed":false},{"to":"856","directed":false},{"to":"830","directed":false},{"to":"697","directed":false},{"to":"828","directed":false},{"to":"713","directed":false},{"to":"819","directed":false},{"to":"747","directed":false},{"to":"774","directed":false},{"to":"805","directed":false}],"features":{"personalData":{"first_name":"Cristina","middle_name":"Julie","last_name":"Goyette","gender":"female","avatar_url":"https://randomuser.me/api/portraits/women/12.jpg"},"workData":{"employer_id":"Schowalter, Balistreri and Kessler","from_id":null,"with_id":null,"location":"55611 New Lindsayview","position":"Customer Marketing Representative","projects":["Awesome Granite Computer","Practical Soft Car"]},"locationData":{"hometown":"05484 Lake Rogelio","location":"55106 Lake Antwan","languages":["English","Zulu"],"locale":"en_US"},"profileDates":{"work_end_date":"2017-01-31T22:01:59.748Z","work_start_date":"2005-09-13T09:16:48.941Z","graduation_date":"2004-10-25T22:32:24.096Z","birth_date":"1984-10-30T22:32:24.000Z"},"coords":{"x":411,"y":167,"z":294}},"coords":{"x":411,"y":167,"z":294}},"856":{"edges":[{"to":"869","directed":false},{"to":"889","directed":false},{"to":"864","directed":false},{"to":"774","directed":false},{"to":"747","directed":false},{"to":"828","directed":false},{"to":"708","directed":false},{"to":"878","directed":false},{"to":"772","directed":false},{"to":"893","directed":false},{"to":"804","directed":false},{"to":"825","directed":false},{"to":"840","directed":false},{"to":"811","directed":false},{"to":"729","directed":false},{"to":"810","directed":false},{"to":"888","directed":false},{"to":"863","directed":false},{"to":"876","directed":false},{"to":"769","directed":false},{"to":"753","directed":false},{"to":"697","directed":false},{"to":"823","directed":false},{"to":"830","directed":false},{"to":"800","directed":false},{"to":"703","directed":false},{"to":"861","directed":false},{"to":"882","directed":false},{"to":"819","directed":false}],"features":{"personalData":{"first_name":"Lindsey","middle_name":"Lilliana","last_name":"Howe","gender":"female","avatar_url":"https://randomuser.me/api/portraits/women/38.jpg"},"workData":{"employer_id":"Hudson, Lakin and Kuvalis","from_id":null,"with_id":null,"location":"12438 Mitchellton","position":"Corporate Data Developer","projects":["Gorgeous Soft Tuna"]},"locationData":{"hometown":"31501 Lake Kasandraside","location":"99994 South Wyattborough","languages":["English","Jin","Serbo-Croatian","Mandarin"],"locale":"en_US"},"profileDates":{"work_end_date":"2015-10-05T02:20:54.598Z","work_start_date":"1997-06-24T13:39:02.670Z","graduation_date":"1996-09-23T18:20:24.883Z","birth_date":"1976-09-28T18:20:24.000Z"},"coords":{"x":215,"y":159,"z":81}},"coords":{"x":215,"y":159,"z":81}},"857":{"edges":[{"to":"865","directed":false},{"to":"868","directed":false},{"to":"871","directed":false},{"to":"862","directed":false}],"features":{"personalData":{"first_name":"Armando","middle_name":"Norbert","last_name":"Ward","gender":"male","avatar_url":"https://randomuser.me/api/portraits/men/80.jpg"},"workData":{"employer_id":"Purdy, Fritsch and Goyette","from_id":null,"with_id":null,"location":"60362 Trantowstad","position":"Investor Identity Representative","projects":["Refined Rubber Table","Licensed Rubber Ball"]},"locationData":{"hometown":"85922 Watersshire","location":"09961 Myaport","languages":["English","German","Maithili","Spanish"],"locale":"en_US"},"profileDates":{"work_end_date":"2015-10-18T10:50:53.269Z","work_start_date":"2009-07-11T19:24:48.943Z","graduation_date":"2008-05-15T00:23:01.038Z","birth_date":"1988-05-20T00:23:01.000Z"},"coords":{"x":338,"y":0,"z":193}},"coords":{"x":338,"y":0,"z":193}},"858":{"edges":[{"to":"881","directed":false},{"to":"870","directed":false},{"to":"895","directed":false},{"to":"871","directed":false}],"features":{"personalData":{"first_name":"Lizeth","middle_name":"Maxie","last_name":"Jaskolski","gender":"female","avatar_url":"https://randomuser.me/api/portraits/women/63.jpg"},"workData":{"employer_id":"Ortiz, Jacobson and Johns","from_id":null,"with_id":null,"location":"37751 New Ludieburgh","position":"Human Group Administrator","projects":["Fantastic Steel Shoes","Generic Fresh Fish"]},"locationData":{"hometown":"15460 East Mac","location":"31116 Ramonamouth","languages":["English","Tamil","Russian","Spanish"],"locale":"en_US"},"profileDates":{"work_end_date":"2016-12-24T12:18:58.047Z","work_start_date":"2011-08-30T09:29:53.355Z","graduation_date":"2011-02-25T04:38:27.149Z","birth_date":"1991-03-02T04:38:27.000Z"},"coords":{"x":461,"y":71,"z":364}},"coords":{"x":461,"y":71,"z":364}},"859":{"edges":[{"to":"885","directed":false}],"features":{"personalData":{"first_name":"Leanne","middle_name":"Lindsey","last_name":"Hane","gender":"female","avatar_url":"https://randomuser.me/api/portraits/women/75.jpg"},"workData":{"employer_id":"Funk LLC","from_id":null,"with_id":null,"location":"81706 Garlandfort","position":"Future Mobility Planner","projects":["Fantastic Fresh Fish","Small Wooden Bike"]},"locationData":{"hometown":"91409 Smithburgh","location":"85262 Lake Rubenborough","languages":["English","Gan","German"],"locale":"en_US"},"profileDates":{"work_end_date":"2016-08-20T02:44:50.918Z","work_start_date":"1999-02-26T01:36:42.666Z","graduation_date":"1997-07-13T04:28:44.893Z","birth_date":"1977-07-18T04:28:44.000Z"},"coords":{"x":302,"y":131,"z":469}},"coords":{"x":302,"y":131,"z":469}},"861":{"edges":[{"to":"863","directed":false},{"to":"729","directed":false},{"to":"889","directed":false},{"to":"804","directed":false},{"to":"888","directed":false},{"to":"753","directed":false},{"to":"878","directed":false},{"to":"856","directed":false},{"to":"876","directed":false}],"features":{"personalData":{"first_name":"Dallas","middle_name":"Raphael","last_name":"Harvey","gender":"male","avatar_url":"https://randomuser.me/api/portraits/men/43.jpg"},"workData":{"employer_id":"Block Inc","from_id":null,"with_id":null,"location":"94057 East Alycialand","position":"Principal Marketing Associate","projects":["Tasty Granite Soap","Ergonomic Concrete Hat","Rustic Wooden Sausages"]},"locationData":{"hometown":"07009 Lake Malvina","location":"52041 South Maxime","languages":["English","Mandarin","Hindi","Spanish","Arabic"],"locale":"en_US"},"profileDates":{"work_end_date":"2017-01-07T15:24:21.657Z","work_start_date":"2005-01-01T17:28:30.419Z","graduation_date":"2003-02-05T02:51:27.510Z","birth_date":"1983-02-10T02:51:27.000Z"},"coords":{"x":193,"y":457,"z":433}},"coords":{"x":193,"y":457,"z":433}},"862":{"edges":[{"to":"868","directed":false},{"to":"865","directed":false},{"to":"857","directed":false}],"features":{"personalData":{"first_name":"Mavis","middle_name":"Graciela","last_name":"Block","gender":"female","avatar_url":"https://randomuser.me/api/portraits/women/93.jpg"},"workData":{"employer_id":"Boehm LLC","from_id":null,"with_id":null,"location":"54609 Uptonstad","position":"Principal Configuration Strategist","projects":["Small Steel Tuna","Sleek Metal Pizza","Refined Rubber Chips"]},"locationData":{"hometown":"03867 Rosellaside","location":"99698 Watersborough","languages":["English","Mandarin"],"locale":"en_US"},"profileDates":{"work_end_date":"2016-10-01T12:26:59.570Z","work_start_date":"2005-04-11T07:50:38.684Z","graduation_date":"2003-07-10T02:31:35.331Z","birth_date":"1983-07-15T02:31:35.000Z"},"coords":{"x":423,"y":449,"z":237}},"coords":{"x":423,"y":449,"z":237}},"863":{"edges":[{"to":"861","directed":false},{"to":"804","directed":false},{"to":"886","directed":false},{"to":"729","directed":false},{"to":"856","directed":false},{"to":"882","directed":false},{"to":"878","directed":false},{"to":"876","directed":false},{"to":"888","directed":false},{"to":"889","directed":false}],"features":{"personalData":{"first_name":"Magdalen","middle_name":"Taryn","last_name":"Cruickshank","gender":"female","avatar_url":"https://randomuser.me/api/portraits/women/15.jpg"},"workData":{"employer_id":"Gislason - Harber","from_id":null,"with_id":null,"location":"67784 Buckridgechester","position":"Customer Accountability Supervisor","projects":["Sleek Metal Sausages","Intelligent Soft Gloves","Ergonomic Soft Computer"]},"locationData":{"hometown":"64447 North Nicholasfort","location":"13954 Scotmouth","languages":["English","Marathi","Hindi"],"locale":"en_US"},"profileDates":{"work_end_date":"2016-07-26T06:36:08.377Z","work_start_date":"1999-08-29T07:20:47.699Z","graduation_date":"1999-01-05T12:48:06.554Z","birth_date":"1979-01-10T12:48:06.000Z"},"coords":{"x":274,"y":290,"z":67}},"coords":{"x":274,"y":290,"z":67}},"864":{"edges":[{"to":"884","directed":false},{"to":"856","directed":false},{"to":"893","directed":false},{"to":"825","directed":false}],"features":{"personalData":{"first_name":"Aurore","middle_name":"Loma","last_name":"Harris","gender":"female","avatar_url":"https://randomuser.me/api/portraits/women/79.jpg"},"workData":{"employer_id":"Monahan, Johnston and Schiller","from_id":null,"with_id":null,"location":"96692 Nitzschebury","position":"Chief Creative Director","projects":["Fantastic Concrete Pizza","Rustic Fresh Computer"]},"locationData":{"hometown":"16015 Hansenberg","location":"02207 Tiannaburgh","languages":["English","Kurdish","Mandarin"],"locale":"en_US"},"profileDates":{"work_end_date":"2016-08-02T01:37:48.747Z","work_start_date":"2001-02-07T08:46:20.747Z","graduation_date":"1999-04-26T02:41:42.807Z","birth_date":"1979-05-01T02:41:42.000Z"},"coords":{"x":171,"y":1,"z":242}},"coords":{"x":171,"y":1,"z":242}},"865":{"edges":[{"to":"857","directed":false},{"to":"868","directed":false},{"to":"862","directed":false}],"features":{"personalData":{"first_name":"Dell","middle_name":"Odessa","last_name":"Kohler","gender":"female","avatar_url":"https://randomuser.me/api/portraits/women/23.jpg"},"workData":{"employer_id":"McCullough LLC","from_id":null,"with_id":null,"location":"76970 West Valliehaven","position":"Principal Infrastructure Assistant","projects":["Refined Cotton Tuna","Handmade Plastic Bike"]},"locationData":{"hometown":"37865 Leonorahaven","location":"72666 Hauckhaven","languages":["English","Mandarin","Spanish","Bengali","Chittagonian"],"locale":"en_US"},"profileDates":{"work_end_date":"2016-08-20T13:15:34.700Z","work_start_date":"2010-07-12T07:48:55.106Z","graduation_date":"2008-12-24T13:33:31.213Z","birth_date":"1988-12-29T13:33:31.000Z"},"coords":{"x":34,"y":417,"z":483}},"coords":{"x":34,"y":417,"z":483}},"866":{"edges":[{"to":"881","directed":false},{"to":"879","directed":false},{"to":"895","directed":false},{"to":"894","directed":false}],"features":{"personalData":{"first_name":"Verla","middle_name":"Georgianna","last_name":"Kassulke","gender":"female","avatar_url":"https://randomuser.me/api/portraits/women/60.jpg"},"workData":{"employer_id":"Koss Inc","from_id":null,"with_id":null,"location":"93205 Richmondhaven","position":"National Creative Agent","projects":["Awesome Steel Hat","Awesome Fresh Bacon","Practical Soft Tuna"]},"locationData":{"hometown":"00229 Leuschkebury","location":"39678 Sengermouth","languages":["English","Urdu"],"locale":"en_US"},"profileDates":{"work_end_date":"2017-01-02T21:19:33.095Z","work_start_date":"2013-06-12T15:50:56.308Z","graduation_date":"2012-11-16T10:29:02.480Z","birth_date":"1992-11-21T10:29:02.000Z"},"coords":{"x":493,"y":411,"z":277}},"coords":{"x":493,"y":411,"z":277}},"867":{"edges":[{"to":"874","directed":false},{"to":"877","directed":false},{"to":"776","directed":false},{"to":"872","directed":false},{"to":"887","directed":false},{"to":"885","directed":false},{"to":"873","directed":false}],"features":{"personalData":{"first_name":"Jarvis","middle_name":"Pierre","last_name":"O'Connell","gender":"male","avatar_url":"https://randomuser.me/api/portraits/men/1.jpg"},"workData":{"employer_id":"Langosh, Stanton and Braun","from_id":null,"with_id":null,"location":"13469 West Brenda","position":"Forward Configuration Producer","projects":["Unbranded Wooden Chicken"]},"locationData":{"hometown":"79475 Port Mabel","location":"41757 South Jordynside","languages":["English","Bengali","Mandarin","Gujarati","Hindi"],"locale":"en_US"},"profileDates":{"work_end_date":"2016-02-11T05:37:18.140Z","work_start_date":"2006-11-15T06:11:57.967Z","graduation_date":"2006-09-30T21:17:25.943Z","birth_date":"1986-10-05T21:17:25.000Z"},"coords":{"x":316,"y":251,"z":443}},"coords":{"x":316,"y":251,"z":443}},"868":{"edges":[{"to":"857","directed":false},{"to":"865","directed":false},{"to":"862","directed":false}],"features":{"personalData":{"first_name":"Lisette","middle_name":"Kristy","last_name":"Olson","gender":"female","avatar_url":"https://randomuser.me/api/portraits/women/51.jpg"},"workData":{"employer_id":"Mann, Orn and Purdy","from_id":null,"with_id":null,"location":"64264 Port Matteo","position":"Customer Usability Agent","projects":["Intelligent Granite Chicken","Licensed Fresh Pants","Sleek Fresh Chips"]},"locationData":{"hometown":"33882 Lake Clifford","location":"62804 East Crystalmouth","languages":["English","Xiang","Sundanese","Russian"],"locale":"en_US"},"profileDates":{"work_end_date":"2015-09-27T17:24:55.268Z","work_start_date":"1999-12-16T01:36:05.704Z","graduation_date":"1999-02-16T19:28:22.347Z","birth_date":"1979-02-21T19:28:22.000Z"},"coords":{"x":90,"y":315,"z":25}},"coords":{"x":90,"y":315,"z":25}},"869":{"edges":[{"to":"856","directed":false},{"to":"774","directed":false},{"to":"769","directed":false},{"to":"708","directed":false},{"to":"811","directed":false},{"to":"890","directed":false}],"features":{"personalData":{"first_name":"Marielle","middle_name":"Cassidy","last_name":"Schimmel","gender":"female","avatar_url":"https://randomuser.me/api/portraits/women/11.jpg"},"workData":{"employer_id":"Jones Inc","from_id":null,"with_id":null,"location":"24073 Port Sandra","position":"Customer Branding Specialist","projects":["Awesome Steel Pizza","Gorgeous Frozen Hat","Unbranded Steel Sausages"]},"locationData":{"hometown":"59252 West Dino","location":"63709 Kevenmouth","languages":["English","Bengali","Portuguese"],"locale":"en_US"},"profileDates":{"work_end_date":"2016-06-05T03:17:10.967Z","work_start_date":"2004-12-15T12:55:26.996Z","graduation_date":"2004-07-18T02:45:46.217Z","birth_date":"1984-07-23T02:45:46.000Z"},"coords":{"x":41,"y":178,"z":420}},"coords":{"x":41,"y":178,"z":420}},"870":{"edges":[{"to":"871","directed":false},{"to":"895","directed":false},{"to":"894","directed":false},{"to":"858","directed":false},{"to":"881","directed":false},{"to":"879","directed":false}],"features":{"personalData":{"first_name":"Anastasia","middle_name":"Leanna","last_name":"Cole","gender":"female","avatar_url":"https://randomuser.me/api/portraits/women/47.jpg"},"workData":{"employer_id":"Zieme LLC","from_id":null,"with_id":null,"location":"54324 Tamarafort","position":"International Brand Executive","projects":["Tasty Granite Keyboard","Incredible Cotton Bike"]},"locationData":{"hometown":"83869 South Eduardoland","location":"70873 West Julio","languages":["English","Korean","Mandarin","Akan"],"locale":"en_US"},"profileDates":{"work_end_date":"2015-09-01T22:54:06.381Z","work_start_date":"1999-12-30T18:49:27.134Z","graduation_date":"1999-10-15T10:21:34.609Z","birth_date":"1979-10-20T10:21:34.000Z"},"coords":{"x":319,"y":301,"z":456}},"coords":{"x":319,"y":301,"z":456}},"871":{"edges":[{"to":"870","directed":false},{"to":"879","directed":false},{"to":"881","directed":false},{"to":"857","directed":false},{"to":"895","directed":false},{"to":"858","directed":false}],"features":{"personalData":{"first_name":"Briana","middle_name":"Sigrid","last_name":"Lesch","gender":"female","avatar_url":"https://randomuser.me/api/portraits/women/12.jpg"},"workData":{"employer_id":"Bauch - Pagac","from_id":null,"with_id":null,"location":"69576 Heathcoteberg","position":"Chief Quality Officer","projects":["Handmade Plastic Sausages","Handmade Frozen Chips"]},"locationData":{"hometown":"70889 New Ariane","location":"00380 Jasttown","languages":["English","Hindi","Gan","Spanish","Japanese"],"locale":"en_US"},"profileDates":{"work_end_date":"2016-03-06T05:18:07.956Z","work_start_date":"2013-01-28T13:15:13.302Z","graduation_date":"2013-01-06T11:25:29.754Z","birth_date":"1993-01-11T11:25:29.000Z"},"coords":{"x":334,"y":213,"z":163}},"coords":{"x":334,"y":213,"z":163}},"872":{"edges":[{"to":"873","directed":false},{"to":"885","directed":false},{"to":"887","directed":false},{"to":"867","directed":false},{"to":"776","directed":false},{"to":"874","directed":false}],"features":{"personalData":{"first_name":"Quentin","middle_name":"Lorenzo","last_name":"Keebler","gender":"male","avatar_url":"https://randomuser.me/api/portraits/men/57.jpg"},"workData":{"employer_id":"Jast Inc","from_id":null,"with_id":null,"location":"81708 Gaylordville","position":"Lead Quality Officer","projects":["Practical Fresh Pizza","Licensed Frozen Chair","Refined Metal Chair"]},"locationData":{"hometown":"00281 Wuckertview","location":"24955 West Percival","languages":["English","Yue","Hindi"],"locale":"en_US"},"profileDates":{"work_end_date":"2016-09-21T07:53:41.010Z","work_start_date":"2015-02-23T21:49:31.215Z","graduation_date":"2014-02-23T21:00:09.251Z","birth_date":"1994-02-28T21:00:09.000Z"},"coords":{"x":505,"y":395,"z":74}},"coords":{"x":505,"y":395,"z":74}},"873":{"edges":[{"to":"872","directed":false},{"to":"874","directed":false},{"to":"776","directed":false},{"to":"885","directed":false},{"to":"867","directed":false}],"features":{"personalData":{"first_name":"Gregory","middle_name":"Darryl","last_name":"Kub","gender":"male","avatar_url":"https://randomuser.me/api/portraits/men/51.jpg"},"workData":{"employer_id":"Emard Group","from_id":null,"with_id":null,"location":"01651 West Zander","position":"Central Interactions Producer","projects":["Fantastic Metal Cheese","Handmade Concrete Pizza"]},"locationData":{"hometown":"97754 Lake Cecilia","location":"17456 Port Edmondburgh","languages":["English","Burmese","Hindi"],"locale":"en_US"},"profileDates":{"work_end_date":"2016-05-04T22:18:50.222Z","work_start_date":"2014-12-08T17:28:34.373Z","graduation_date":"2013-07-27T18:40:30.640Z","birth_date":"1993-08-01T18:40:30.000Z"},"coords":{"x":348,"y":297,"z":330}},"coords":{"x":348,"y":297,"z":330}},"874":{"edges":[{"to":"873","directed":false},{"to":"776","directed":false},{"to":"867","directed":false},{"to":"887","directed":false},{"to":"885","directed":false},{"to":"872","directed":false}],"features":{"personalData":{"first_name":"Maudie","middle_name":"Wanda","last_name":"Denesik","gender":"female","avatar_url":"https://randomuser.me/api/portraits/women/61.jpg"},"workData":{"employer_id":"Walsh - Bechtelar","from_id":null,"with_id":null,"location":"55439 East Cadeport","position":"Investor Usability Administrator","projects":["Unbranded Plastic Pants","Incredible Wooden Bike","Intelligent Fresh Car"]},"locationData":{"hometown":"91682 Marlenberg","location":"12436 Robertsmouth","languages":["English","Sindhi"],"locale":"en_US"},"profileDates":{"work_end_date":"2016-07-09T15:26:47.341Z","work_start_date":"2005-01-15T13:58:45.597Z","graduation_date":"2003-03-08T05:46:12.025Z","birth_date":"1983-03-13T05:46:12.000Z"},"coords":{"x":476,"y":480,"z":359}},"coords":{"x":476,"y":480,"z":359}},"876":{"edges":[{"to":"729","directed":false},{"to":"889","directed":false},{"to":"886","directed":false},{"to":"804","directed":false},{"to":"888","directed":false},{"to":"856","directed":false},{"to":"882","directed":false},{"to":"863","directed":false},{"to":"861","directed":false},{"to":"878","directed":false}],"features":{"personalData":{"first_name":"Ericka","middle_name":"Justina","last_name":"O'Conner","gender":"female","avatar_url":"https://randomuser.me/api/portraits/women/73.jpg"},"workData":{"employer_id":"Aufderhar - Berge","from_id":null,"with_id":null,"location":"41709 Nataliabury","position":"District Security Planner","projects":["Sleek Rubber Cheese","Licensed Granite Computer"]},"locationData":{"hometown":"86095 Lebsackmouth","location":"17343 New Flossieberg","languages":["English","Southern"],"locale":"en_US"},"profileDates":{"work_end_date":"2015-08-09T02:47:38.476Z","work_start_date":"1999-09-23T10:13:21.574Z","graduation_date":"1998-06-15T05:54:38.626Z","birth_date":"1978-06-20T05:54:38.000Z"},"coords":{"x":306,"y":355,"z":120}},"coords":{"x":306,"y":355,"z":120}},"877":{"edges":[{"to":"867","directed":false},{"to":"885","directed":false},{"to":"776","directed":false}],"features":{"personalData":{"first_name":"Marie","middle_name":"Hillary","last_name":"Conn","gender":"female","avatar_url":"https://randomuser.me/api/portraits/women/25.jpg"},"workData":{"employer_id":"Tromp, Streich and Weissnat","from_id":null,"with_id":null,"location":"54117 Wuckertport","position":"Lead Solutions Designer","projects":["Fantastic Frozen Cheese","Handmade Plastic Soap"]},"locationData":{"hometown":"27614 West Yvonnetown","location":"75471 Jastchester","languages":["English","Yue"],"locale":"en_US"},"profileDates":{"work_end_date":"2015-08-25T06:54:07.857Z","work_start_date":"2013-11-17T06:05:07.942Z","graduation_date":"2012-05-02T13:01:35.434Z","birth_date":"1992-05-07T13:01:35.000Z"},"coords":{"x":334,"y":230,"z":498}},"coords":{"x":334,"y":230,"z":498}},"878":{"edges":[{"to":"889","directed":false},{"to":"856","directed":false},{"to":"886","directed":false},{"to":"888","directed":false},{"to":"804","directed":false},{"to":"729","directed":false},{"to":"861","directed":false},{"to":"863","directed":false},{"to":"876","directed":false}],"features":{"personalData":{"first_name":"Hope","middle_name":"Ocie","last_name":"Ondricka","gender":"female","avatar_url":"https://randomuser.me/api/portraits/women/20.jpg"},"workData":{"employer_id":"Bergstrom Inc","from_id":null,"with_id":null,"location":"46955 West Pinkie","position":"Global Factors Liason","projects":["Fantastic Granite Mouse","Handmade Fresh Towels"]},"locationData":{"hometown":"93460 Denastad","location":"46629 Port Tianna","languages":["English","Arabic","Zhuang","Spanish","Xiang"],"locale":"en_US"},"profileDates":{"work_end_date":"2017-01-30T07:37:48.410Z","work_start_date":"2003-01-31T01:40:56.141Z","graduation_date":"2002-04-02T14:02:38.041Z","birth_date":"1982-04-07T14:02:38.000Z"},"coords":{"x":280,"y":169,"z":125}},"coords":{"x":280,"y":169,"z":125}},"879":{"edges":[{"to":"871","directed":false},{"to":"881","directed":false},{"to":"894","directed":false},{"to":"866","directed":false},{"to":"870","directed":false}],"features":{"personalData":{"first_name":"Oswaldo","middle_name":"Clair","last_name":"Hane","gender":"male","avatar_url":"https://randomuser.me/api/portraits/men/7.jpg"},"workData":{"employer_id":"Rau Group","from_id":null,"with_id":null,"location":"45695 Gleichnermouth","position":"District Configuration Architect","projects":["Rustic Fresh Hat","Small Concrete Bacon","Fantastic Plastic Mouse"]},"locationData":{"hometown":"17010 Jerdehaven","location":"89934 Lake Keeleyhaven","languages":["English","Bengali","Mandarin","Tamil"],"locale":"en_US"},"profileDates":{"work_end_date":"2016-06-29T14:38:43.592Z","work_start_date":"2003-07-27T18:28:58.439Z","graduation_date":"2003-06-13T22:55:40.423Z","birth_date":"1983-06-18T22:55:40.000Z"},"coords":{"x":0,"y":237,"z":144}},"coords":{"x":0,"y":237,"z":144}},"880":{"edges":[{"to":"828","directed":false},{"to":"819","directed":false},{"to":"805","directed":false},{"to":"823","directed":false},{"to":"747","directed":false},{"to":"803","directed":false},{"to":"703","directed":false}],"features":{"personalData":{"first_name":"Meghan","middle_name":"Joana","last_name":"Cronin","gender":"female","avatar_url":"https://randomuser.me/api/portraits/women/9.jpg"},"workData":{"employer_id":"Huels, Hayes and Gleason","from_id":null,"with_id":null,"location":"48314 Issacview","position":"Dynamic Optimization Supervisor","projects":["Awesome Concrete Towels"]},"locationData":{"hometown":"51858 East Tremaine","location":"78406 Daytonhaven","languages":["English","Thai","French","Bengali"],"locale":"en_US"},"profileDates":{"work_end_date":"2016-08-12T13:57:33.704Z","work_start_date":"2015-01-28T03:54:48.257Z","graduation_date":"2014-12-22T12:21:10.921Z","birth_date":"1994-12-27T12:21:10.000Z"},"coords":{"x":180,"y":247,"z":72}},"coords":{"x":180,"y":247,"z":72}},"881":{"edges":[{"to":"858","directed":false},{"to":"895","directed":false},{"to":"879","directed":false},{"to":"871","directed":false},{"to":"866","directed":false},{"to":"870","directed":false}],"features":{"personalData":{"first_name":"Terrance","middle_name":"German","last_name":"Hilpert","gender":"male","avatar_url":"https://randomuser.me/api/portraits/men/52.jpg"},"workData":{"employer_id":"Auer, Orn and Stracke","from_id":null,"with_id":null,"location":"72040 Creminshire","position":"District Response Producer","projects":["Incredible Rubber Towels","Handmade Steel Ball","Handcrafted Rubber Bacon"]},"locationData":{"hometown":"15071 New Jabariville","location":"79967 East Neoma","languages":["English","Russian","Hindi"],"locale":"en_US"},"profileDates":{"work_end_date":"2016-05-10T12:47:42.391Z","work_start_date":"2010-12-12T22:14:50.498Z","graduation_date":"2009-06-22T04:04:47.009Z","birth_date":"1989-06-27T04:04:47.000Z"},"coords":{"x":502,"y":346,"z":407}},"coords":{"x":502,"y":346,"z":407}},"882":{"edges":[{"to":"729","directed":false},{"to":"804","directed":false},{"to":"863","directed":false},{"to":"876","directed":false},{"to":"889","directed":false},{"to":"856","directed":false},{"to":"886","directed":false}],"features":{"personalData":{"first_name":"Hubert","middle_name":"Curtis","last_name":"Yost","gender":"male","avatar_url":"https://randomuser.me/api/portraits/men/39.jpg"},"workData":{"employer_id":"Olson Group","from_id":null,"with_id":null,"location":"96650 Port Keiraborough","position":"Forward Interactions Director","projects":["Licensed Metal Soap"]},"locationData":{"hometown":"02951 Port Nya","location":"54925 East Orie","languages":["English","Mandarin","Hindi"],"locale":"en_US"},"profileDates":{"work_end_date":"2016-07-21T05:11:55.577Z","work_start_date":"2006-12-13T10:42:13.683Z","graduation_date":"2005-04-06T13:27:37.448Z","birth_date":"1985-04-11T13:27:37.000Z"},"coords":{"x":336,"y":231,"z":18}},"coords":{"x":336,"y":231,"z":18}},"884":{"edges":[{"to":"864","directed":false},{"to":"825","directed":false},{"to":"893","directed":false}],"features":{"personalData":{"first_name":"Manuela","middle_name":"Dawn","last_name":"Waelchi","gender":"female","avatar_url":"https://randomuser.me/api/portraits/women/36.jpg"},"workData":{"employer_id":"Orn, Schaefer and Johns","from_id":null,"with_id":null,"location":"46062 Port Alexa","position":"Internal Metrics Analyst","projects":["Gorgeous Steel Tuna","Sleek Metal Towels"]},"locationData":{"hometown":"01276 Kilbackmouth","location":"60029 South Savionchester","languages":["English","Pashto","Hindi"],"locale":"en_US"},"profileDates":{"work_end_date":"2017-01-21T19:23:50.217Z","work_start_date":"2006-02-12T07:15:05.542Z","graduation_date":"2004-05-18T15:03:14.602Z","birth_date":"1984-05-23T15:03:14.000Z"},"coords":{"x":92,"y":141,"z":303}},"coords":{"x":92,"y":141,"z":303}},"885":{"edges":[{"to":"872","directed":false},{"to":"859","directed":false},{"to":"877","directed":false},{"to":"873","directed":false},{"to":"776","directed":false},{"to":"874","directed":false},{"to":"867","directed":false},{"to":"887","directed":false}],"features":{"personalData":{"first_name":"Della","middle_name":"Regan","last_name":"Morissette","gender":"female","avatar_url":"https://randomuser.me/api/portraits/women/11.jpg"},"workData":{"employer_id":"Conn, Waters and Rolfson","from_id":null,"with_id":null,"location":"17732 Danielfort","position":"Customer Configuration Analyst","projects":["Practical Granite Bike","Handmade Fresh Keyboard"]},"locationData":{"hometown":"51889 Billfort","location":"67346 North Mariahbury","languages":["English","Malayalam","Russian","Amharic"],"locale":"en_US"},"profileDates":{"work_end_date":"2016-06-20T17:00:07.370Z","work_start_date":"2009-06-15T03:22:36.199Z","graduation_date":"2008-10-22T06:27:02.440Z","birth_date":"1988-10-27T06:27:02.000Z"},"coords":{"x":53,"y":297,"z":23}},"coords":{"x":53,"y":297,"z":23}},"886":{"edges":[{"to":"889","directed":false},{"to":"863","directed":false},{"to":"729","directed":false},{"to":"876","directed":false},{"to":"878","directed":false},{"to":"804","directed":false},{"to":"882","directed":false}],"features":{"personalData":{"first_name":"Kari","middle_name":"Kacey","last_name":"Ryan","gender":"female","avatar_url":"https://randomuser.me/api/portraits/women/38.jpg"},"workData":{"employer_id":"Johnston Group","from_id":null,"with_id":null,"location":"54778 Christiansenfort","position":"District Markets Associate","projects":["Unbranded Wooden Chair","Ergonomic Granite Chips","Handmade Wooden Chicken"]},"locationData":{"hometown":"76116 Nicolasville","location":"57093 Kirlinstad","languages":["English","Igbo"],"locale":"en_US"},"profileDates":{"work_end_date":"2015-07-23T09:33:06.396Z","work_start_date":"2014-10-14T22:53:33.307Z","graduation_date":"2014-05-08T01:22:30.334Z","birth_date":"1994-05-13T01:22:30.000Z"},"coords":{"x":357,"y":129,"z":45}},"coords":{"x":357,"y":129,"z":45}},"887":{"edges":[{"to":"872","directed":false},{"to":"874","directed":false},{"to":"776","directed":false},{"to":"867","directed":false},{"to":"885","directed":false}],"features":{"personalData":{"first_name":"Alfredo","middle_name":"Kristofer","last_name":"Hegmann","gender":"male","avatar_url":"https://randomuser.me/api/portraits/men/30.jpg"},"workData":{"employer_id":"Schowalter - Greenholt","from_id":null,"with_id":null,"location":"81560 South Benny","position":"Future Identity Facilitator","projects":["Refined Rubber Ball","Rustic Granite Chicken","Tasty Metal Sausages"]},"locationData":{"hometown":"71238 Emmerichmouth","location":"65392 Batzville","languages":["English","Kazakh","Mandarin","Bengali"],"locale":"en_US"},"profileDates":{"work_end_date":"2016-01-10T03:44:13.891Z","work_start_date":"2004-09-01T16:19:18.693Z","graduation_date":"2003-04-15T21:08:44.594Z","birth_date":"1983-04-20T21:08:44.000Z"},"coords":{"x":505,"y":82,"z":7}},"coords":{"x":505,"y":82,"z":7}},"888":{"edges":[{"to":"889","directed":false},{"to":"729","directed":false},{"to":"804","directed":false},{"to":"861","directed":false},{"to":"856","directed":false},{"to":"876","directed":false},{"to":"878","directed":false},{"to":"863","directed":false}],"features":{"personalData":{"first_name":"Brenna","middle_name":"Maegan","last_name":"Hayes","gender":"female","avatar_url":"https://randomuser.me/api/portraits/women/0.jpg"},"workData":{"employer_id":"Schuster - Pfannerstill","from_id":null,"with_id":null,"location":"10828 Hesterberg","position":"Legacy Applications Analyst","projects":["Gorgeous Steel Chips","Intelligent Metal Pizza","Gorgeous Fresh Ball"]},"locationData":{"hometown":"35012 Crystalberg","location":"91835 New Mosesview","languages":["English","Hindi"],"locale":"en_US"},"profileDates":{"work_end_date":"2015-11-21T01:40:42.474Z","work_start_date":"2002-10-26T22:07:58.973Z","graduation_date":"2001-07-02T17:52:23.030Z","birth_date":"1981-07-07T17:52:23.000Z"},"coords":{"x":482,"y":433,"z":281}},"coords":{"x":482,"y":433,"z":281}},"889":{"edges":[{"to":"856","directed":false},{"to":"888","directed":false},{"to":"825","directed":false},{"to":"886","directed":false},{"to":"861","directed":false},{"to":"878","directed":false},{"to":"753","directed":false},{"to":"876","directed":false},{"to":"729","directed":false},{"to":"882","directed":false},{"to":"863","directed":false},{"to":"804","directed":false}],"features":{"personalData":{"first_name":"Haley","middle_name":"Layla","last_name":"Kunde","gender":"female","avatar_url":"https://randomuser.me/api/portraits/women/81.jpg"},"workData":{"employer_id":"Kihn Inc","from_id":null,"with_id":null,"location":"16177 New Kirashire","position":"Legacy Paradigm Analyst","projects":["Gorgeous Soft Gloves","Generic Fresh Towels"]},"locationData":{"hometown":"28321 Zemlakborough","location":"66599 Lake Katheryntown","languages":["English","Mandarin","Kurdish","Spanish"],"locale":"en_US"},"profileDates":{"work_end_date":"2016-07-09T08:27:23.800Z","work_start_date":"2014-01-12T01:50:39.946Z","graduation_date":"2013-07-29T11:32:58.099Z","birth_date":"1993-08-03T11:32:58.000Z"},"coords":{"x":491,"y":174,"z":50}},"coords":{"x":491,"y":174,"z":50}},"890":{"edges":[{"to":"697","directed":false},{"to":"753","directed":false},{"to":"708","directed":false},{"to":"811","directed":false},{"to":"869","directed":false},{"to":"769","directed":false}],"features":{"personalData":{"first_name":"Nicolette","middle_name":"Trisha","last_name":"Zemlak","gender":"female","avatar_url":"https://randomuser.me/api/portraits/women/65.jpg"},"workData":{"employer_id":"Mueller - Dooley","from_id":null,"with_id":null,"location":"49016 Germaineside","position":"Human Integration Officer","projects":["Handmade Rubber Salad","Licensed Wooden Fish","Small Concrete Pants"]},"locationData":{"hometown":"76768 Daltonfurt","location":"47827 North Patricia","languages":["English","Somali","Portuguese","Mandarin"],"locale":"en_US"},"profileDates":{"work_end_date":"2016-08-30T03:22:02.047Z","work_start_date":"2011-05-18T13:06:59.603Z","graduation_date":"2009-09-05T07:54:06.708Z","birth_date":"1989-09-10T07:54:06.000Z"},"coords":{"x":206,"y":255,"z":462}},"coords":{"x":206,"y":255,"z":462}},"893":{"edges":[{"to":"864","directed":false},{"to":"856","directed":false},{"to":"884","directed":false}],"features":{"personalData":{"first_name":"Dortha","middle_name":"Kenna","last_name":"Botsford","gender":"female","avatar_url":"https://randomuser.me/api/portraits/women/7.jpg"},"workData":{"employer_id":"Ondricka, Stracke and Sanford","from_id":null,"with_id":null,"location":"81168 East Cobymouth","position":"Product Functionality Technician","projects":["Gorgeous Granite Chicken"]},"locationData":{"hometown":"35970 North Richiemouth","location":"85823 North Myrtice","languages":["English","Portuguese","Arabic","Marathi"],"locale":"en_US"},"profileDates":{"work_end_date":"2016-08-15T09:20:54.414Z","work_start_date":"2012-01-21T23:36:41.395Z","graduation_date":"2010-04-22T13:48:49.036Z","birth_date":"1990-04-27T13:48:49.000Z"},"coords":{"x":230,"y":440,"z":73}},"coords":{"x":230,"y":440,"z":73}},"894":{"edges":[{"to":"879","directed":false},{"to":"870","directed":false},{"to":"866","directed":false}],"features":{"personalData":{"first_name":"Kirsten","middle_name":"Althea","last_name":"Huels","gender":"female","avatar_url":"https://randomuser.me/api/portraits/women/61.jpg"},"workData":{"employer_id":"Gutmann Inc","from_id":null,"with_id":null,"location":"70789 West Evert","position":"Investor Markets Technician","projects":["Generic Steel Chair","Refined Metal Salad"]},"locationData":{"hometown":"30476 Champlinshire","location":"11202 Jessikachester","languages":["English","Mandarin","Hindi","Assamese","Gujarati"],"locale":"en_US"},"profileDates":{"work_end_date":"2015-10-13T08:42:45.845Z","work_start_date":"2004-05-08T10:45:28.297Z","graduation_date":"2003-06-17T10:13:32.522Z","birth_date":"1983-06-22T10:13:32.000Z"},"coords":{"x":96,"y":155,"z":105}},"coords":{"x":96,"y":155,"z":105}},"895":{"edges":[{"to":"881","directed":false},{"to":"870","directed":false},{"to":"871","directed":false},{"to":"866","directed":false},{"to":"858","directed":false}],"features":{"personalData":{"first_name":"Elliot","middle_name":"Ricardo","last_name":"Murazik","gender":"male","avatar_url":"https://randomuser.me/api/portraits/men/59.jpg"},"workData":{"employer_id":"McClure - Bergstrom","from_id":null,"with_id":null,"location":"32345 Adamsville","position":"Forward Integration Architect","projects":["Unbranded Granite Table","Licensed Plastic Pizza"]},"locationData":{"hometown":"71117 Lake Horace","location":"87335 Lake Niafurt","languages":["English","Burmese"],"locale":"en_US"},"profileDates":{"work_end_date":"2015-10-03T04:49:46.743Z","work_start_date":"1997-02-14T21:06:47.608Z","graduation_date":"1995-10-21T15:57:52.571Z","birth_date":"1975-10-26T15:57:52.000Z"},"coords":{"x":435,"y":41,"z":313}},"coords":{"x":435,"y":41,"z":313}}}}